[
  {
    "url": "https://api.github.com/repos/grpc/grpc/issues/comments/365996163",
    "html_url": "https://github.com/grpc/grpc/pull/14437#issuecomment-365996163",
    "issue_url": "https://api.github.com/repos/grpc/grpc/issues/14437",
    "id": 365996163,
    "node_id": "MDEyOklzc3VlQ29tbWVudDM2NTk5NjE2Mw==",
    "user": {
      "login": "grpc-testing",
      "id": 28024233,
      "node_id": "MDQ6VXNlcjI4MDI0MjMz",
      "avatar_url": "https://avatars1.githubusercontent.com/u/28024233?v=4",
      "gravatar_id": "",
      "url": "https://api.github.com/users/grpc-testing",
      "html_url": "https://github.com/grpc-testing",
      "followers_url": "https://api.github.com/users/grpc-testing/followers",
      "following_url": "https://api.github.com/users/grpc-testing/following{/other_user}",
      "gists_url": "https://api.github.com/users/grpc-testing/gists{/gist_id}",
      "starred_url": "https://api.github.com/users/grpc-testing/starred{/owner}{/repo}",
      "subscriptions_url": "https://api.github.com/users/grpc-testing/subscriptions",
      "organizations_url": "https://api.github.com/users/grpc-testing/orgs",
      "repos_url": "https://api.github.com/users/grpc-testing/repos",
      "events_url": "https://api.github.com/users/grpc-testing/events{/privacy}",
      "received_events_url": "https://api.github.com/users/grpc-testing/received_events",
      "type": "User",
      "site_admin": false
    },
    "created_at": "2018-02-15T17:11:38Z",
    "updated_at": "2018-02-15T17:11:38Z",
    "author_association": "NONE",
    "body": "```\n****************************************************************\n\nlibgrpc.so\n\n     VM SIZE                                                                                            FILE SIZE\n ++++++++++++++ GROWING                                                                              ++++++++++++++\n  [NEW] +8.82Ki src/core/lib/security/security_connector/security_connector.cc                       +8.82Ki  [NEW]\n      [NEW] +1.92Ki [Other]                                                                              +1.92Ki  [NEW]\n      [NEW]    +666 grpc_ssl_channel_security_connector_create                                              +666  [NEW]\n      [NEW]    +629 try_fetch_ssl_server_credentials                                                        +629  [NEW]\n      [NEW]    +537 fake_check_peer(grpc_security_connector*, tsi_peer, grpc_auth_context**, grpc_closur    +537  [NEW]\n      [NEW]    +526 fake_channel_check_peer                                                                 +526  [NEW]\n      [NEW]    +518 tsi_shallow_peer_from_ssl_auth_context                                                  +518  [NEW]\n      [NEW]    +500 grpc_ssl_server_security_connector_create                                               +500  [NEW]\n      [NEW]    +492 [Unmapped]                                                                              +492  [NEW]\n      [NEW]    +452 compute_default_pem_root_certs_once                                                     +452  [NEW]\n      [NEW]    +409 tsi_ssl_peer_to_auth_context                                                            +409  [NEW]\n      [NEW]    +404 ssl_check_peer(grpc_security_connector*, char const*, tsi_peer const*, grpc_auth_con    +404  [NEW]\n      [NEW]    +343 fake_check_target                                                                       +343  [NEW]\n      [NEW]    +216 grpc_channel_security_connector_cmp                                                     +216  [NEW]\n      [NEW]    +202 ssl_channel_check_call_host                                                             +202  [NEW]\n      [NEW]    +183 grpc_security_connector_check_peer                                                      +183  [NEW]\n      [NEW]    +182 ssl_channel_add_handshakers                                                             +182  [NEW]\n      [NEW]    +176 grpc_fake_channel_security_connector_create                                             +176  [NEW]\n      [NEW]    +166 grpc_channel_security_connector_check_call_host                                         +166  [NEW]\n      [NEW]    +160 ssl_server_add_handshakers                                                              +160  [NEW]\n      [NEW]    +154 grpc_server_security_connector_cmp                                                      +154  [NEW]\n      [NEW]    +146 ssl_host_matches_name                                                                   +146  [NEW]\n  [ = ]       0 [None]                                                                                  +480  +0.0%\n\n -------------- SHRINKING                                                                            --------------\n  [DEL] -8.82Ki src/core/lib/security/transport/security_connector.cc                                -8.82Ki  [DEL]\n      [DEL] -1.92Ki [Other]                                                                              -1.92Ki  [DEL]\n      [DEL]    -666 grpc_ssl_channel_security_connector_create                                              -666  [DEL]\n      [DEL]    -629 try_fetch_ssl_server_credentials                                                        -629  [DEL]\n      [DEL]    -537 fake_check_peer(grpc_security_connector*, tsi_peer, grpc_auth_context**, grpc_closur    -537  [DEL]\n      [DEL]    -526 fake_channel_check_peer                                                                 -526  [DEL]\n      [DEL]    -518 tsi_shallow_peer_from_ssl_auth_context                                                  -518  [DEL]\n      [DEL]    -500 grpc_ssl_server_security_connector_create                                               -500  [DEL]\n      [DEL]    -492 [Unmapped]                                                                              -492  [DEL]\n      [DEL]    -452 compute_default_pem_root_certs_once                                                     -452  [DEL]\n      [DEL]    -409 tsi_ssl_peer_to_auth_context                                                            -409  [DEL]\n      [DEL]    -404 ssl_check_peer(grpc_security_connector*, char const*, tsi_peer const*, grpc_auth_con    -404  [DEL]\n      [DEL]    -343 fake_check_target                                                                       -343  [DEL]\n      [DEL]    -216 grpc_channel_security_connector_cmp                                                     -216  [DEL]\n      [DEL]    -202 ssl_channel_check_call_host                                                             -202  [DEL]\n      [DEL]    -183 grpc_security_connector_check_peer                                                      -183  [DEL]\n      [DEL]    -182 ssl_channel_add_handshakers                                                             -182  [DEL]\n      [DEL]    -176 grpc_fake_channel_security_connector_create                                             -176  [DEL]\n      [DEL]    -166 grpc_channel_security_connector_check_call_host                                         -166  [DEL]\n      [DEL]    -160 ssl_server_add_handshakers                                                              -160  [DEL]\n      [DEL]    -154 grpc_server_security_connector_cmp                                                      -154  [DEL]\n      [DEL]    -146 ssl_host_matches_name                                                                   -146  [DEL]\n\n  [ = ]       0 TOTAL                                                                                   +480  +0.0%\n\n\n****************************************************************\n\nlibgrpc++.so\n\n     VM SIZE        FILE SIZE\n ++++++++++++++  ++++++++++++++\n\n  [ = ]       0        0  [ = ]\n\n\n\n```"
  },
  {
    "url": "https://api.github.com/repos/grpc/grpc/issues/comments/365998862",
    "html_url": "https://github.com/grpc/grpc/pull/14437#issuecomment-365998862",
    "issue_url": "https://api.github.com/repos/grpc/grpc/issues/14437",
    "id": 365998862,
    "node_id": "MDEyOklzc3VlQ29tbWVudDM2NTk5ODg2Mg==",
    "user": {
      "login": "grpc-testing",
      "id": 28024233,
      "node_id": "MDQ6VXNlcjI4MDI0MjMz",
      "avatar_url": "https://avatars1.githubusercontent.com/u/28024233?v=4",
      "gravatar_id": "",
      "url": "https://api.github.com/users/grpc-testing",
      "html_url": "https://github.com/grpc-testing",
      "followers_url": "https://api.github.com/users/grpc-testing/followers",
      "following_url": "https://api.github.com/users/grpc-testing/following{/other_user}",
      "gists_url": "https://api.github.com/users/grpc-testing/gists{/gist_id}",
      "starred_url": "https://api.github.com/users/grpc-testing/starred{/owner}{/repo}",
      "subscriptions_url": "https://api.github.com/users/grpc-testing/subscriptions",
      "organizations_url": "https://api.github.com/users/grpc-testing/orgs",
      "repos_url": "https://api.github.com/users/grpc-testing/repos",
      "events_url": "https://api.github.com/users/grpc-testing/events{/privacy}",
      "received_events_url": "https://api.github.com/users/grpc-testing/received_events",
      "type": "User",
      "site_admin": false
    },
    "created_at": "2018-02-15T17:20:23Z",
    "updated_at": "2018-02-15T17:20:23Z",
    "author_association": "NONE",
    "body": "```\n[trickle] No significant performance differences\n```"
  },
  {
    "url": "https://api.github.com/repos/grpc/grpc/issues/comments/366011804",
    "html_url": "https://github.com/grpc/grpc/pull/14437#issuecomment-366011804",
    "issue_url": "https://api.github.com/repos/grpc/grpc/issues/14437",
    "id": 366011804,
    "node_id": "MDEyOklzc3VlQ29tbWVudDM2NjAxMTgwNA==",
    "user": {
      "login": "grpc-testing",
      "id": 28024233,
      "node_id": "MDQ6VXNlcjI4MDI0MjMz",
      "avatar_url": "https://avatars1.githubusercontent.com/u/28024233?v=4",
      "gravatar_id": "",
      "url": "https://api.github.com/users/grpc-testing",
      "html_url": "https://github.com/grpc-testing",
      "followers_url": "https://api.github.com/users/grpc-testing/followers",
      "following_url": "https://api.github.com/users/grpc-testing/following{/other_user}",
      "gists_url": "https://api.github.com/users/grpc-testing/gists{/gist_id}",
      "starred_url": "https://api.github.com/users/grpc-testing/starred{/owner}{/repo}",
      "subscriptions_url": "https://api.github.com/users/grpc-testing/subscriptions",
      "organizations_url": "https://api.github.com/users/grpc-testing/orgs",
      "repos_url": "https://api.github.com/users/grpc-testing/repos",
      "events_url": "https://api.github.com/users/grpc-testing/events{/privacy}",
      "received_events_url": "https://api.github.com/users/grpc-testing/received_events",
      "type": "User",
      "site_admin": false
    },
    "created_at": "2018-02-15T18:05:25Z",
    "updated_at": "2018-02-15T18:05:25Z",
    "author_association": "NONE",
    "body": "```\n[microbenchmarks] No significant performance differences\n```"
  },
  {
    "url": "https://api.github.com/repos/grpc/grpc/issues/comments/366086847",
    "html_url": "https://github.com/grpc/grpc/pull/14437#issuecomment-366086847",
    "issue_url": "https://api.github.com/repos/grpc/grpc/issues/14437",
    "id": 366086847,
    "node_id": "MDEyOklzc3VlQ29tbWVudDM2NjA4Njg0Nw==",
    "user": {
      "login": "markdroth",
      "id": 18664614,
      "node_id": "MDQ6VXNlcjE4NjY0NjE0",
      "avatar_url": "https://avatars2.githubusercontent.com/u/18664614?v=4",
      "gravatar_id": "",
      "url": "https://api.github.com/users/markdroth",
      "html_url": "https://github.com/markdroth",
      "followers_url": "https://api.github.com/users/markdroth/followers",
      "following_url": "https://api.github.com/users/markdroth/following{/other_user}",
      "gists_url": "https://api.github.com/users/markdroth/gists{/gist_id}",
      "starred_url": "https://api.github.com/users/markdroth/starred{/owner}{/repo}",
      "subscriptions_url": "https://api.github.com/users/markdroth/subscriptions",
      "organizations_url": "https://api.github.com/users/markdroth/orgs",
      "repos_url": "https://api.github.com/users/markdroth/repos",
      "events_url": "https://api.github.com/users/markdroth/events{/privacy}",
      "received_events_url": "https://api.github.com/users/markdroth/received_events",
      "type": "User",
      "site_admin": false
    },
    "created_at": "2018-02-15T22:43:45Z",
    "updated_at": "2018-02-15T22:43:45Z",
    "author_association": "MEMBER",
    "body": "Looks like there's still a bug in the BUILD file.  You'll need to fix that before this can be merged."
  },
  {
    "url": "https://api.github.com/repos/grpc/grpc/issues/comments/366091578",
    "html_url": "https://github.com/grpc/grpc/pull/14437#issuecomment-366091578",
    "issue_url": "https://api.github.com/repos/grpc/grpc/issues/14437",
    "id": 366091578,
    "node_id": "MDEyOklzc3VlQ29tbWVudDM2NjA5MTU3OA==",
    "user": {
      "login": "grpc-testing",
      "id": 28024233,
      "node_id": "MDQ6VXNlcjI4MDI0MjMz",
      "avatar_url": "https://avatars1.githubusercontent.com/u/28024233?v=4",
      "gravatar_id": "",
      "url": "https://api.github.com/users/grpc-testing",
      "html_url": "https://github.com/grpc-testing",
      "followers_url": "https://api.github.com/users/grpc-testing/followers",
      "following_url": "https://api.github.com/users/grpc-testing/following{/other_user}",
      "gists_url": "https://api.github.com/users/grpc-testing/gists{/gist_id}",
      "starred_url": "https://api.github.com/users/grpc-testing/starred{/owner}{/repo}",
      "subscriptions_url": "https://api.github.com/users/grpc-testing/subscriptions",
      "organizations_url": "https://api.github.com/users/grpc-testing/orgs",
      "repos_url": "https://api.github.com/users/grpc-testing/repos",
      "events_url": "https://api.github.com/users/grpc-testing/events{/privacy}",
      "received_events_url": "https://api.github.com/users/grpc-testing/received_events",
      "type": "User",
      "site_admin": false
    },
    "created_at": "2018-02-15T23:02:53Z",
    "updated_at": "2018-02-15T23:02:53Z",
    "author_association": "NONE",
    "body": "```\n****************************************************************\n\nlibgrpc.so\n\n     VM SIZE                                                                                            FILE SIZE\n ++++++++++++++ GROWING                                                                              ++++++++++++++\n  [NEW] +8.82Ki src/core/lib/security/security_connector/security_connector.cc                       +8.82Ki  [NEW]\n      [NEW] +1.92Ki [Other]                                                                              +1.92Ki  [NEW]\n      [NEW]    +666 grpc_ssl_channel_security_connector_create                                              +666  [NEW]\n      [NEW]    +629 try_fetch_ssl_server_credentials                                                        +629  [NEW]\n      [NEW]    +537 fake_check_peer(grpc_security_connector*, tsi_peer, grpc_auth_context**, grpc_closur    +537  [NEW]\n      [NEW]    +526 fake_channel_check_peer                                                                 +526  [NEW]\n      [NEW]    +518 tsi_shallow_peer_from_ssl_auth_context                                                  +518  [NEW]\n      [NEW]    +500 grpc_ssl_server_security_connector_create                                               +500  [NEW]\n      [NEW]    +492 [Unmapped]                                                                              +492  [NEW]\n      [NEW]    +452 compute_default_pem_root_certs_once                                                     +452  [NEW]\n      [NEW]    +409 tsi_ssl_peer_to_auth_context                                                            +409  [NEW]\n      [NEW]    +404 ssl_check_peer(grpc_security_connector*, char const*, tsi_peer const*, grpc_auth_con    +404  [NEW]\n      [NEW]    +343 fake_check_target                                                                       +343  [NEW]\n      [NEW]    +216 grpc_channel_security_connector_cmp                                                     +216  [NEW]\n      [NEW]    +202 ssl_channel_check_call_host                                                             +202  [NEW]\n      [NEW]    +183 grpc_security_connector_check_peer                                                      +183  [NEW]\n      [NEW]    +182 ssl_channel_add_handshakers                                                             +182  [NEW]\n      [NEW]    +176 grpc_fake_channel_security_connector_create                                             +176  [NEW]\n      [NEW]    +166 grpc_channel_security_connector_check_call_host                                         +166  [NEW]\n      [NEW]    +160 ssl_server_add_handshakers                                                              +160  [NEW]\n      [NEW]    +154 grpc_server_security_connector_cmp                                                      +154  [NEW]\n      [NEW]    +146 ssl_host_matches_name                                                                   +146  [NEW]\n  [ = ]       0 [None]                                                                                  +480  +0.0%\n\n -------------- SHRINKING                                                                            --------------\n  [DEL] -8.82Ki src/core/lib/security/transport/security_connector.cc                                -8.82Ki  [DEL]\n      [DEL] -1.92Ki [Other]                                                                              -1.92Ki  [DEL]\n      [DEL]    -666 grpc_ssl_channel_security_connector_create                                              -666  [DEL]\n      [DEL]    -629 try_fetch_ssl_server_credentials                                                        -629  [DEL]\n      [DEL]    -537 fake_check_peer(grpc_security_connector*, tsi_peer, grpc_auth_context**, grpc_closur    -537  [DEL]\n      [DEL]    -526 fake_channel_check_peer                                                                 -526  [DEL]\n      [DEL]    -518 tsi_shallow_peer_from_ssl_auth_context                                                  -518  [DEL]\n      [DEL]    -500 grpc_ssl_server_security_connector_create                                               -500  [DEL]\n      [DEL]    -492 [Unmapped]                                                                              -492  [DEL]\n      [DEL]    -452 compute_default_pem_root_certs_once                                                     -452  [DEL]\n      [DEL]    -409 tsi_ssl_peer_to_auth_context                                                            -409  [DEL]\n      [DEL]    -404 ssl_check_peer(grpc_security_connector*, char const*, tsi_peer const*, grpc_auth_con    -404  [DEL]\n      [DEL]    -343 fake_check_target                                                                       -343  [DEL]\n      [DEL]    -216 grpc_channel_security_connector_cmp                                                     -216  [DEL]\n      [DEL]    -202 ssl_channel_check_call_host                                                             -202  [DEL]\n      [DEL]    -183 grpc_security_connector_check_peer                                                      -183  [DEL]\n      [DEL]    -182 ssl_channel_add_handshakers                                                             -182  [DEL]\n      [DEL]    -176 grpc_fake_channel_security_connector_create                                             -176  [DEL]\n      [DEL]    -166 grpc_channel_security_connector_check_call_host                                         -166  [DEL]\n      [DEL]    -160 ssl_server_add_handshakers                                                              -160  [DEL]\n      [DEL]    -154 grpc_server_security_connector_cmp                                                      -154  [DEL]\n      [DEL]    -146 ssl_host_matches_name                                                                   -146  [DEL]\n\n  [ = ]       0 TOTAL                                                                                   +480  +0.0%\n\n\n****************************************************************\n\nlibgrpc++.so\n\n     VM SIZE        FILE SIZE\n ++++++++++++++  ++++++++++++++\n\n  [ = ]       0        0  [ = ]\n\n\n\n```"
  },
  {
    "url": "https://api.github.com/repos/grpc/grpc/issues/comments/366093642",
    "html_url": "https://github.com/grpc/grpc/pull/14437#issuecomment-366093642",
    "issue_url": "https://api.github.com/repos/grpc/grpc/issues/14437",
    "id": 366093642,
    "node_id": "MDEyOklzc3VlQ29tbWVudDM2NjA5MzY0Mg==",
    "user": {
      "login": "grpc-testing",
      "id": 28024233,
      "node_id": "MDQ6VXNlcjI4MDI0MjMz",
      "avatar_url": "https://avatars1.githubusercontent.com/u/28024233?v=4",
      "gravatar_id": "",
      "url": "https://api.github.com/users/grpc-testing",
      "html_url": "https://github.com/grpc-testing",
      "followers_url": "https://api.github.com/users/grpc-testing/followers",
      "following_url": "https://api.github.com/users/grpc-testing/following{/other_user}",
      "gists_url": "https://api.github.com/users/grpc-testing/gists{/gist_id}",
      "starred_url": "https://api.github.com/users/grpc-testing/starred{/owner}{/repo}",
      "subscriptions_url": "https://api.github.com/users/grpc-testing/subscriptions",
      "organizations_url": "https://api.github.com/users/grpc-testing/orgs",
      "repos_url": "https://api.github.com/users/grpc-testing/repos",
      "events_url": "https://api.github.com/users/grpc-testing/events{/privacy}",
      "received_events_url": "https://api.github.com/users/grpc-testing/received_events",
      "type": "User",
      "site_admin": false
    },
    "created_at": "2018-02-15T23:12:28Z",
    "updated_at": "2018-02-15T23:12:28Z",
    "author_association": "NONE",
    "body": "```\n[trickle] No significant performance differences\n```"
  },
  {
    "url": "https://api.github.com/repos/grpc/grpc/issues/comments/366102216",
    "html_url": "https://github.com/grpc/grpc/pull/14437#issuecomment-366102216",
    "issue_url": "https://api.github.com/repos/grpc/grpc/issues/14437",
    "id": 366102216,
    "node_id": "MDEyOklzc3VlQ29tbWVudDM2NjEwMjIxNg==",
    "user": {
      "login": "grpc-testing",
      "id": 28024233,
      "node_id": "MDQ6VXNlcjI4MDI0MjMz",
      "avatar_url": "https://avatars1.githubusercontent.com/u/28024233?v=4",
      "gravatar_id": "",
      "url": "https://api.github.com/users/grpc-testing",
      "html_url": "https://github.com/grpc-testing",
      "followers_url": "https://api.github.com/users/grpc-testing/followers",
      "following_url": "https://api.github.com/users/grpc-testing/following{/other_user}",
      "gists_url": "https://api.github.com/users/grpc-testing/gists{/gist_id}",
      "starred_url": "https://api.github.com/users/grpc-testing/starred{/owner}{/repo}",
      "subscriptions_url": "https://api.github.com/users/grpc-testing/subscriptions",
      "organizations_url": "https://api.github.com/users/grpc-testing/orgs",
      "repos_url": "https://api.github.com/users/grpc-testing/repos",
      "events_url": "https://api.github.com/users/grpc-testing/events{/privacy}",
      "received_events_url": "https://api.github.com/users/grpc-testing/received_events",
      "type": "User",
      "site_admin": false
    },
    "created_at": "2018-02-15T23:55:31Z",
    "updated_at": "2018-02-15T23:55:31Z",
    "author_association": "NONE",
    "body": "```\n[microbenchmarks] No significant performance differences\n```"
  },
  {
    "url": "https://api.github.com/repos/grpc/grpc/issues/comments/366371045",
    "html_url": "https://github.com/grpc/grpc/pull/14437#issuecomment-366371045",
    "issue_url": "https://api.github.com/repos/grpc/grpc/issues/14437",
    "id": 366371045,
    "node_id": "MDEyOklzc3VlQ29tbWVudDM2NjM3MTA0NQ==",
    "user": {
      "login": "yihuazhang",
      "id": 26934891,
      "node_id": "MDQ6VXNlcjI2OTM0ODkx",
      "avatar_url": "https://avatars2.githubusercontent.com/u/26934891?v=4",
      "gravatar_id": "",
      "url": "https://api.github.com/users/yihuazhang",
      "html_url": "https://github.com/yihuazhang",
      "followers_url": "https://api.github.com/users/yihuazhang/followers",
      "following_url": "https://api.github.com/users/yihuazhang/following{/other_user}",
      "gists_url": "https://api.github.com/users/yihuazhang/gists{/gist_id}",
      "starred_url": "https://api.github.com/users/yihuazhang/starred{/owner}{/repo}",
      "subscriptions_url": "https://api.github.com/users/yihuazhang/subscriptions",
      "organizations_url": "https://api.github.com/users/yihuazhang/orgs",
      "repos_url": "https://api.github.com/users/yihuazhang/repos",
      "events_url": "https://api.github.com/users/yihuazhang/events{/privacy}",
      "received_events_url": "https://api.github.com/users/yihuazhang/received_events",
      "type": "User",
      "site_admin": false
    },
    "created_at": "2018-02-16T22:01:19Z",
    "updated_at": "2018-02-16T22:01:19Z",
    "author_association": "CONTRIBUTOR",
    "body": "F.Y.I. All tests passed, and I think it is ready to get merged."
  },
  {
    "url": "https://api.github.com/repos/grpc/grpc/issues/comments/366401726",
    "html_url": "https://github.com/grpc/grpc/pull/14437#issuecomment-366401726",
    "issue_url": "https://api.github.com/repos/grpc/grpc/issues/14437",
    "id": 366401726,
    "node_id": "MDEyOklzc3VlQ29tbWVudDM2NjQwMTcyNg==",
    "user": {
      "login": "grpc-testing",
      "id": 28024233,
      "node_id": "MDQ6VXNlcjI4MDI0MjMz",
      "avatar_url": "https://avatars1.githubusercontent.com/u/28024233?v=4",
      "gravatar_id": "",
      "url": "https://api.github.com/users/grpc-testing",
      "html_url": "https://github.com/grpc-testing",
      "followers_url": "https://api.github.com/users/grpc-testing/followers",
      "following_url": "https://api.github.com/users/grpc-testing/following{/other_user}",
      "gists_url": "https://api.github.com/users/grpc-testing/gists{/gist_id}",
      "starred_url": "https://api.github.com/users/grpc-testing/starred{/owner}{/repo}",
      "subscriptions_url": "https://api.github.com/users/grpc-testing/subscriptions",
      "organizations_url": "https://api.github.com/users/grpc-testing/orgs",
      "repos_url": "https://api.github.com/users/grpc-testing/repos",
      "events_url": "https://api.github.com/users/grpc-testing/events{/privacy}",
      "received_events_url": "https://api.github.com/users/grpc-testing/received_events",
      "type": "User",
      "site_admin": false
    },
    "created_at": "2018-02-17T01:07:54Z",
    "updated_at": "2018-02-17T01:07:54Z",
    "author_association": "NONE",
    "body": "```\n****************************************************************\n\nlibgrpc.so\n\n     VM SIZE                                                                                            FILE SIZE\n ++++++++++++++ GROWING                                                                              ++++++++++++++\n  [NEW] +8.82Ki src/core/lib/security/security_connector/security_connector.cc                       +8.82Ki  [NEW]\n      [NEW] +1.92Ki [Other]                                                                              +1.92Ki  [NEW]\n      [NEW]    +666 grpc_ssl_channel_security_connector_create                                              +666  [NEW]\n      [NEW]    +629 try_fetch_ssl_server_credentials                                                        +629  [NEW]\n      [NEW]    +537 fake_check_peer(grpc_security_connector*, tsi_peer, grpc_auth_context**, grpc_closur    +537  [NEW]\n      [NEW]    +526 fake_channel_check_peer                                                                 +526  [NEW]\n      [NEW]    +518 tsi_shallow_peer_from_ssl_auth_context                                                  +518  [NEW]\n      [NEW]    +500 grpc_ssl_server_security_connector_create                                               +500  [NEW]\n      [NEW]    +492 [Unmapped]                                                                              +492  [NEW]\n      [NEW]    +452 compute_default_pem_root_certs_once                                                     +452  [NEW]\n      [NEW]    +409 tsi_ssl_peer_to_auth_context                                                            +409  [NEW]\n      [NEW]    +404 ssl_check_peer(grpc_security_connector*, char const*, tsi_peer const*, grpc_auth_con    +404  [NEW]\n      [NEW]    +343 fake_check_target                                                                       +343  [NEW]\n      [NEW]    +216 grpc_channel_security_connector_cmp                                                     +216  [NEW]\n      [NEW]    +202 ssl_channel_check_call_host                                                             +202  [NEW]\n      [NEW]    +183 grpc_security_connector_check_peer                                                      +183  [NEW]\n      [NEW]    +182 ssl_channel_add_handshakers                                                             +182  [NEW]\n      [NEW]    +176 grpc_fake_channel_security_connector_create                                             +176  [NEW]\n      [NEW]    +166 grpc_channel_security_connector_check_call_host                                         +166  [NEW]\n      [NEW]    +160 ssl_server_add_handshakers                                                              +160  [NEW]\n      [NEW]    +154 grpc_server_security_connector_cmp                                                      +154  [NEW]\n      [NEW]    +146 ssl_host_matches_name                                                                   +146  [NEW]\n  [ = ]       0 [None]                                                                                  +480  +0.0%\n\n -------------- SHRINKING                                                                            --------------\n  [DEL] -8.82Ki src/core/lib/security/transport/security_connector.cc                                -8.82Ki  [DEL]\n      [DEL] -1.92Ki [Other]                                                                              -1.92Ki  [DEL]\n      [DEL]    -666 grpc_ssl_channel_security_connector_create                                              -666  [DEL]\n      [DEL]    -629 try_fetch_ssl_server_credentials                                                        -629  [DEL]\n      [DEL]    -537 fake_check_peer(grpc_security_connector*, tsi_peer, grpc_auth_context**, grpc_closur    -537  [DEL]\n      [DEL]    -526 fake_channel_check_peer                                                                 -526  [DEL]\n      [DEL]    -518 tsi_shallow_peer_from_ssl_auth_context                                                  -518  [DEL]\n      [DEL]    -500 grpc_ssl_server_security_connector_create                                               -500  [DEL]\n      [DEL]    -492 [Unmapped]                                                                              -492  [DEL]\n      [DEL]    -452 compute_default_pem_root_certs_once                                                     -452  [DEL]\n      [DEL]    -409 tsi_ssl_peer_to_auth_context                                                            -409  [DEL]\n      [DEL]    -404 ssl_check_peer(grpc_security_connector*, char const*, tsi_peer const*, grpc_auth_con    -404  [DEL]\n      [DEL]    -343 fake_check_target                                                                       -343  [DEL]\n      [DEL]    -216 grpc_channel_security_connector_cmp                                                     -216  [DEL]\n      [DEL]    -202 ssl_channel_check_call_host                                                             -202  [DEL]\n      [DEL]    -183 grpc_security_connector_check_peer                                                      -183  [DEL]\n      [DEL]    -182 ssl_channel_add_handshakers                                                             -182  [DEL]\n      [DEL]    -176 grpc_fake_channel_security_connector_create                                             -176  [DEL]\n      [DEL]    -166 grpc_channel_security_connector_check_call_host                                         -166  [DEL]\n      [DEL]    -160 ssl_server_add_handshakers                                                              -160  [DEL]\n      [DEL]    -154 grpc_server_security_connector_cmp                                                      -154  [DEL]\n      [DEL]    -146 ssl_host_matches_name                                                                   -146  [DEL]\n\n  [ = ]       0 TOTAL                                                                                   +480  +0.0%\n\n\n****************************************************************\n\nlibgrpc++.so\n\n     VM SIZE        FILE SIZE\n ++++++++++++++  ++++++++++++++\n\n  [ = ]       0        0  [ = ]\n\n\n\n```"
  },
  {
    "url": "https://api.github.com/repos/grpc/grpc/issues/comments/366402422",
    "html_url": "https://github.com/grpc/grpc/pull/14437#issuecomment-366402422",
    "issue_url": "https://api.github.com/repos/grpc/grpc/issues/14437",
    "id": 366402422,
    "node_id": "MDEyOklzc3VlQ29tbWVudDM2NjQwMjQyMg==",
    "user": {
      "login": "grpc-testing",
      "id": 28024233,
      "node_id": "MDQ6VXNlcjI4MDI0MjMz",
      "avatar_url": "https://avatars1.githubusercontent.com/u/28024233?v=4",
      "gravatar_id": "",
      "url": "https://api.github.com/users/grpc-testing",
      "html_url": "https://github.com/grpc-testing",
      "followers_url": "https://api.github.com/users/grpc-testing/followers",
      "following_url": "https://api.github.com/users/grpc-testing/following{/other_user}",
      "gists_url": "https://api.github.com/users/grpc-testing/gists{/gist_id}",
      "starred_url": "https://api.github.com/users/grpc-testing/starred{/owner}{/repo}",
      "subscriptions_url": "https://api.github.com/users/grpc-testing/subscriptions",
      "organizations_url": "https://api.github.com/users/grpc-testing/orgs",
      "repos_url": "https://api.github.com/users/grpc-testing/repos",
      "events_url": "https://api.github.com/users/grpc-testing/events{/privacy}",
      "received_events_url": "https://api.github.com/users/grpc-testing/received_events",
      "type": "User",
      "site_admin": false
    },
    "created_at": "2018-02-17T01:15:22Z",
    "updated_at": "2018-02-17T01:15:22Z",
    "author_association": "NONE",
    "body": "```\n[trickle] No significant performance differences\n```"
  },
  {
    "url": "https://api.github.com/repos/grpc/grpc/issues/comments/366406934",
    "html_url": "https://github.com/grpc/grpc/pull/14437#issuecomment-366406934",
    "issue_url": "https://api.github.com/repos/grpc/grpc/issues/14437",
    "id": 366406934,
    "node_id": "MDEyOklzc3VlQ29tbWVudDM2NjQwNjkzNA==",
    "user": {
      "login": "grpc-testing",
      "id": 28024233,
      "node_id": "MDQ6VXNlcjI4MDI0MjMz",
      "avatar_url": "https://avatars1.githubusercontent.com/u/28024233?v=4",
      "gravatar_id": "",
      "url": "https://api.github.com/users/grpc-testing",
      "html_url": "https://github.com/grpc-testing",
      "followers_url": "https://api.github.com/users/grpc-testing/followers",
      "following_url": "https://api.github.com/users/grpc-testing/following{/other_user}",
      "gists_url": "https://api.github.com/users/grpc-testing/gists{/gist_id}",
      "starred_url": "https://api.github.com/users/grpc-testing/starred{/owner}{/repo}",
      "subscriptions_url": "https://api.github.com/users/grpc-testing/subscriptions",
      "organizations_url": "https://api.github.com/users/grpc-testing/orgs",
      "repos_url": "https://api.github.com/users/grpc-testing/repos",
      "events_url": "https://api.github.com/users/grpc-testing/events{/privacy}",
      "received_events_url": "https://api.github.com/users/grpc-testing/received_events",
      "type": "User",
      "site_admin": false
    },
    "created_at": "2018-02-17T02:01:24Z",
    "updated_at": "2018-02-17T02:01:24Z",
    "author_association": "NONE",
    "body": "```\n[microbenchmarks] No significant performance differences\n```"
  },
  {
    "url": "https://api.github.com/repos/grpc/grpc/issues/comments/367067876",
    "html_url": "https://github.com/grpc/grpc/pull/14437#issuecomment-367067876",
    "issue_url": "https://api.github.com/repos/grpc/grpc/issues/14437",
    "id": 367067876,
    "node_id": "MDEyOklzc3VlQ29tbWVudDM2NzA2Nzg3Ng==",
    "user": {
      "login": "grpc-testing",
      "id": 28024233,
      "node_id": "MDQ6VXNlcjI4MDI0MjMz",
      "avatar_url": "https://avatars1.githubusercontent.com/u/28024233?v=4",
      "gravatar_id": "",
      "url": "https://api.github.com/users/grpc-testing",
      "html_url": "https://github.com/grpc-testing",
      "followers_url": "https://api.github.com/users/grpc-testing/followers",
      "following_url": "https://api.github.com/users/grpc-testing/following{/other_user}",
      "gists_url": "https://api.github.com/users/grpc-testing/gists{/gist_id}",
      "starred_url": "https://api.github.com/users/grpc-testing/starred{/owner}{/repo}",
      "subscriptions_url": "https://api.github.com/users/grpc-testing/subscriptions",
      "organizations_url": "https://api.github.com/users/grpc-testing/orgs",
      "repos_url": "https://api.github.com/users/grpc-testing/repos",
      "events_url": "https://api.github.com/users/grpc-testing/events{/privacy}",
      "received_events_url": "https://api.github.com/users/grpc-testing/received_events",
      "type": "User",
      "site_admin": false
    },
    "created_at": "2018-02-20T18:13:34Z",
    "updated_at": "2018-02-20T18:13:34Z",
    "author_association": "NONE",
    "body": "```\n****************************************************************\n\nlibgrpc.so\n\n     VM SIZE                                                                                            FILE SIZE\n ++++++++++++++ GROWING                                                                              ++++++++++++++\n  [NEW] +8.82Ki src/core/lib/security/security_connector/security_connector.cc                       +8.82Ki  [NEW]\n      [NEW] +1.92Ki [Other]                                                                              +1.92Ki  [NEW]\n      [NEW]    +666 grpc_ssl_channel_security_connector_create                                              +666  [NEW]\n      [NEW]    +629 try_fetch_ssl_server_credentials                                                        +629  [NEW]\n      [NEW]    +537 fake_check_peer(grpc_security_connector*, tsi_peer, grpc_auth_context**, grpc_closur    +537  [NEW]\n      [NEW]    +526 fake_channel_check_peer                                                                 +526  [NEW]\n      [NEW]    +518 tsi_shallow_peer_from_ssl_auth_context                                                  +518  [NEW]\n      [NEW]    +500 grpc_ssl_server_security_connector_create                                               +500  [NEW]\n      [NEW]    +492 [Unmapped]                                                                              +492  [NEW]\n      [NEW]    +452 compute_default_pem_root_certs_once                                                     +452  [NEW]\n      [NEW]    +409 tsi_ssl_peer_to_auth_context                                                            +409  [NEW]\n      [NEW]    +404 ssl_check_peer(grpc_security_connector*, char const*, tsi_peer const*, grpc_auth_con    +404  [NEW]\n      [NEW]    +343 fake_check_target                                                                       +343  [NEW]\n      [NEW]    +216 grpc_channel_security_connector_cmp                                                     +216  [NEW]\n      [NEW]    +202 ssl_channel_check_call_host                                                             +202  [NEW]\n      [NEW]    +183 grpc_security_connector_check_peer                                                      +183  [NEW]\n      [NEW]    +182 ssl_channel_add_handshakers                                                             +182  [NEW]\n      [NEW]    +176 grpc_fake_channel_security_connector_create                                             +176  [NEW]\n      [NEW]    +166 grpc_channel_security_connector_check_call_host                                         +166  [NEW]\n      [NEW]    +160 ssl_server_add_handshakers                                                              +160  [NEW]\n      [NEW]    +154 grpc_server_security_connector_cmp                                                      +154  [NEW]\n      [NEW]    +146 ssl_host_matches_name                                                                   +146  [NEW]\n  [ = ]       0 [None]                                                                                  +480  +0.0%\n\n -------------- SHRINKING                                                                            --------------\n  [DEL] -8.82Ki src/core/lib/security/transport/security_connector.cc                                -8.82Ki  [DEL]\n      [DEL] -1.92Ki [Other]                                                                              -1.92Ki  [DEL]\n      [DEL]    -666 grpc_ssl_channel_security_connector_create                                              -666  [DEL]\n      [DEL]    -629 try_fetch_ssl_server_credentials                                                        -629  [DEL]\n      [DEL]    -537 fake_check_peer(grpc_security_connector*, tsi_peer, grpc_auth_context**, grpc_closur    -537  [DEL]\n      [DEL]    -526 fake_channel_check_peer                                                                 -526  [DEL]\n      [DEL]    -518 tsi_shallow_peer_from_ssl_auth_context                                                  -518  [DEL]\n      [DEL]    -500 grpc_ssl_server_security_connector_create                                               -500  [DEL]\n      [DEL]    -492 [Unmapped]                                                                              -492  [DEL]\n      [DEL]    -452 compute_default_pem_root_certs_once                                                     -452  [DEL]\n      [DEL]    -409 tsi_ssl_peer_to_auth_context                                                            -409  [DEL]\n      [DEL]    -404 ssl_check_peer(grpc_security_connector*, char const*, tsi_peer const*, grpc_auth_con    -404  [DEL]\n      [DEL]    -343 fake_check_target                                                                       -343  [DEL]\n      [DEL]    -216 grpc_channel_security_connector_cmp                                                     -216  [DEL]\n      [DEL]    -202 ssl_channel_check_call_host                                                             -202  [DEL]\n      [DEL]    -183 grpc_security_connector_check_peer                                                      -183  [DEL]\n      [DEL]    -182 ssl_channel_add_handshakers                                                             -182  [DEL]\n      [DEL]    -176 grpc_fake_channel_security_connector_create                                             -176  [DEL]\n      [DEL]    -166 grpc_channel_security_connector_check_call_host                                         -166  [DEL]\n      [DEL]    -160 ssl_server_add_handshakers                                                              -160  [DEL]\n      [DEL]    -154 grpc_server_security_connector_cmp                                                      -154  [DEL]\n      [DEL]    -146 ssl_host_matches_name                                                                   -146  [DEL]\n\n  [ = ]       0 TOTAL                                                                                   +480  +0.0%\n\n\n****************************************************************\n\nlibgrpc++.so\n\n     VM SIZE        FILE SIZE\n ++++++++++++++  ++++++++++++++\n\n  [ = ]       0        0  [ = ]\n\n\n\n```"
  },
  {
    "url": "https://api.github.com/repos/grpc/grpc/issues/comments/367070250",
    "html_url": "https://github.com/grpc/grpc/pull/14437#issuecomment-367070250",
    "issue_url": "https://api.github.com/repos/grpc/grpc/issues/14437",
    "id": 367070250,
    "node_id": "MDEyOklzc3VlQ29tbWVudDM2NzA3MDI1MA==",
    "user": {
      "login": "grpc-testing",
      "id": 28024233,
      "node_id": "MDQ6VXNlcjI4MDI0MjMz",
      "avatar_url": "https://avatars1.githubusercontent.com/u/28024233?v=4",
      "gravatar_id": "",
      "url": "https://api.github.com/users/grpc-testing",
      "html_url": "https://github.com/grpc-testing",
      "followers_url": "https://api.github.com/users/grpc-testing/followers",
      "following_url": "https://api.github.com/users/grpc-testing/following{/other_user}",
      "gists_url": "https://api.github.com/users/grpc-testing/gists{/gist_id}",
      "starred_url": "https://api.github.com/users/grpc-testing/starred{/owner}{/repo}",
      "subscriptions_url": "https://api.github.com/users/grpc-testing/subscriptions",
      "organizations_url": "https://api.github.com/users/grpc-testing/orgs",
      "repos_url": "https://api.github.com/users/grpc-testing/repos",
      "events_url": "https://api.github.com/users/grpc-testing/events{/privacy}",
      "received_events_url": "https://api.github.com/users/grpc-testing/received_events",
      "type": "User",
      "site_admin": false
    },
    "created_at": "2018-02-20T18:21:31Z",
    "updated_at": "2018-02-20T18:21:31Z",
    "author_association": "NONE",
    "body": "```\n[trickle] No significant performance differences\n```"
  },
  {
    "url": "https://api.github.com/repos/grpc/grpc/issues/comments/367083867",
    "html_url": "https://github.com/grpc/grpc/pull/14437#issuecomment-367083867",
    "issue_url": "https://api.github.com/repos/grpc/grpc/issues/14437",
    "id": 367083867,
    "node_id": "MDEyOklzc3VlQ29tbWVudDM2NzA4Mzg2Nw==",
    "user": {
      "login": "grpc-testing",
      "id": 28024233,
      "node_id": "MDQ6VXNlcjI4MDI0MjMz",
      "avatar_url": "https://avatars1.githubusercontent.com/u/28024233?v=4",
      "gravatar_id": "",
      "url": "https://api.github.com/users/grpc-testing",
      "html_url": "https://github.com/grpc-testing",
      "followers_url": "https://api.github.com/users/grpc-testing/followers",
      "following_url": "https://api.github.com/users/grpc-testing/following{/other_user}",
      "gists_url": "https://api.github.com/users/grpc-testing/gists{/gist_id}",
      "starred_url": "https://api.github.com/users/grpc-testing/starred{/owner}{/repo}",
      "subscriptions_url": "https://api.github.com/users/grpc-testing/subscriptions",
      "organizations_url": "https://api.github.com/users/grpc-testing/orgs",
      "repos_url": "https://api.github.com/users/grpc-testing/repos",
      "events_url": "https://api.github.com/users/grpc-testing/events{/privacy}",
      "received_events_url": "https://api.github.com/users/grpc-testing/received_events",
      "type": "User",
      "site_admin": false
    },
    "created_at": "2018-02-20T19:05:52Z",
    "updated_at": "2018-02-20T19:05:52Z",
    "author_association": "NONE",
    "body": "```\n[microbenchmarks] No significant performance differences\n```"
  },
  {
    "url": "https://api.github.com/repos/grpc/grpc/issues/comments/367385583",
    "html_url": "https://github.com/grpc/grpc/pull/14437#issuecomment-367385583",
    "issue_url": "https://api.github.com/repos/grpc/grpc/issues/14437",
    "id": 367385583,
    "node_id": "MDEyOklzc3VlQ29tbWVudDM2NzM4NTU4Mw==",
    "user": {
      "login": "markdroth",
      "id": 18664614,
      "node_id": "MDQ6VXNlcjE4NjY0NjE0",
      "avatar_url": "https://avatars2.githubusercontent.com/u/18664614?v=4",
      "gravatar_id": "",
      "url": "https://api.github.com/users/markdroth",
      "html_url": "https://github.com/markdroth",
      "followers_url": "https://api.github.com/users/markdroth/followers",
      "following_url": "https://api.github.com/users/markdroth/following{/other_user}",
      "gists_url": "https://api.github.com/users/markdroth/gists{/gist_id}",
      "starred_url": "https://api.github.com/users/markdroth/starred{/owner}{/repo}",
      "subscriptions_url": "https://api.github.com/users/markdroth/subscriptions",
      "organizations_url": "https://api.github.com/users/markdroth/orgs",
      "repos_url": "https://api.github.com/users/markdroth/repos",
      "events_url": "https://api.github.com/users/markdroth/events{/privacy}",
      "received_events_url": "https://api.github.com/users/markdroth/received_events",
      "type": "User",
      "site_admin": false
    },
    "created_at": "2018-02-21T16:31:28Z",
    "updated_at": "2018-02-21T16:31:28Z",
    "author_association": "MEMBER",
    "body": "As a follow-up, it would probably be a good idea to move the fake and SSL security connector implementations out of security_connector.{h,cc} and into their own subdirectories."
  },
  {
    "url": "https://api.github.com/repos/grpc/grpc/issues/comments/367402848",
    "html_url": "https://github.com/grpc/grpc/pull/14437#issuecomment-367402848",
    "issue_url": "https://api.github.com/repos/grpc/grpc/issues/14437",
    "id": 367402848,
    "node_id": "MDEyOklzc3VlQ29tbWVudDM2NzQwMjg0OA==",
    "user": {
      "login": "yihuazhang",
      "id": 26934891,
      "node_id": "MDQ6VXNlcjI2OTM0ODkx",
      "avatar_url": "https://avatars2.githubusercontent.com/u/26934891?v=4",
      "gravatar_id": "",
      "url": "https://api.github.com/users/yihuazhang",
      "html_url": "https://github.com/yihuazhang",
      "followers_url": "https://api.github.com/users/yihuazhang/followers",
      "following_url": "https://api.github.com/users/yihuazhang/following{/other_user}",
      "gists_url": "https://api.github.com/users/yihuazhang/gists{/gist_id}",
      "starred_url": "https://api.github.com/users/yihuazhang/starred{/owner}{/repo}",
      "subscriptions_url": "https://api.github.com/users/yihuazhang/subscriptions",
      "organizations_url": "https://api.github.com/users/yihuazhang/orgs",
      "repos_url": "https://api.github.com/users/yihuazhang/repos",
      "events_url": "https://api.github.com/users/yihuazhang/events{/privacy}",
      "received_events_url": "https://api.github.com/users/yihuazhang/received_events",
      "type": "User",
      "site_admin": false
    },
    "created_at": "2018-02-21T17:22:22Z",
    "updated_at": "2018-02-21T17:22:22Z",
    "author_association": "CONTRIBUTOR",
    "body": "Sure, I will work on refactoring the security connector for fake and SSL from security_connector.{h, cc}. "
  }
]
