[
  {
    "url": "https://api.github.com/repos/pandas-dev/pandas/issues/comments/383551773",
    "html_url": "https://github.com/pandas-dev/pandas/pull/20794#issuecomment-383551773",
    "issue_url": "https://api.github.com/repos/pandas-dev/pandas/issues/20794",
    "id": 383551773,
    "node_id": "MDEyOklzc3VlQ29tbWVudDM4MzU1MTc3Mw==",
    "user": {
      "login": "jorisvandenbossche",
      "id": 1020496,
      "node_id": "MDQ6VXNlcjEwMjA0OTY=",
      "avatar_url": "https://avatars2.githubusercontent.com/u/1020496?v=4",
      "gravatar_id": "",
      "url": "https://api.github.com/users/jorisvandenbossche",
      "html_url": "https://github.com/jorisvandenbossche",
      "followers_url": "https://api.github.com/users/jorisvandenbossche/followers",
      "following_url": "https://api.github.com/users/jorisvandenbossche/following{/other_user}",
      "gists_url": "https://api.github.com/users/jorisvandenbossche/gists{/gist_id}",
      "starred_url": "https://api.github.com/users/jorisvandenbossche/starred{/owner}{/repo}",
      "subscriptions_url": "https://api.github.com/users/jorisvandenbossche/subscriptions",
      "organizations_url": "https://api.github.com/users/jorisvandenbossche/orgs",
      "repos_url": "https://api.github.com/users/jorisvandenbossche/repos",
      "events_url": "https://api.github.com/users/jorisvandenbossche/events{/privacy}",
      "received_events_url": "https://api.github.com/users/jorisvandenbossche/received_events",
      "type": "User",
      "site_admin": false
    },
    "created_at": "2018-04-23T12:06:12Z",
    "updated_at": "2018-04-23T12:06:12Z",
    "author_association": "MEMBER",
    "body": "This is a temporary \"fix\" to the interface. \r\nLong term solution would be to make sure we don't make such assumptions internally, but that would need to fix all places where we currently check for a `_values` or `values` attribute, which is much more work (as often it is actually a way to have code be generic for eg both Series and EA/ndarray, as `_values` on the Series then returns the underlying EA/ndarray)."
  },
  {
    "url": "https://api.github.com/repos/pandas-dev/pandas/issues/comments/383552249",
    "html_url": "https://github.com/pandas-dev/pandas/pull/20794#issuecomment-383552249",
    "issue_url": "https://api.github.com/repos/pandas-dev/pandas/issues/20794",
    "id": 383552249,
    "node_id": "MDEyOklzc3VlQ29tbWVudDM4MzU1MjI0OQ==",
    "user": {
      "login": "jorisvandenbossche",
      "id": 1020496,
      "node_id": "MDQ6VXNlcjEwMjA0OTY=",
      "avatar_url": "https://avatars2.githubusercontent.com/u/1020496?v=4",
      "gravatar_id": "",
      "url": "https://api.github.com/users/jorisvandenbossche",
      "html_url": "https://github.com/jorisvandenbossche",
      "followers_url": "https://api.github.com/users/jorisvandenbossche/followers",
      "following_url": "https://api.github.com/users/jorisvandenbossche/following{/other_user}",
      "gists_url": "https://api.github.com/users/jorisvandenbossche/gists{/gist_id}",
      "starred_url": "https://api.github.com/users/jorisvandenbossche/starred{/owner}{/repo}",
      "subscriptions_url": "https://api.github.com/users/jorisvandenbossche/subscriptions",
      "organizations_url": "https://api.github.com/users/jorisvandenbossche/orgs",
      "repos_url": "https://api.github.com/users/jorisvandenbossche/repos",
      "events_url": "https://api.github.com/users/jorisvandenbossche/events{/privacy}",
      "received_events_url": "https://api.github.com/users/jorisvandenbossche/received_events",
      "type": "User",
      "site_admin": false
    },
    "created_at": "2018-04-23T12:08:16Z",
    "updated_at": "2018-04-23T12:08:16Z",
    "author_association": "MEMBER",
    "body": "Ah, see you just did the same https://github.com/pandas-dev/pandas/pull/20793 :-)"
  },
  {
    "url": "https://api.github.com/repos/pandas-dev/pandas/issues/comments/383561206",
    "html_url": "https://github.com/pandas-dev/pandas/pull/20794#issuecomment-383561206",
    "issue_url": "https://api.github.com/repos/pandas-dev/pandas/issues/20794",
    "id": 383561206,
    "node_id": "MDEyOklzc3VlQ29tbWVudDM4MzU2MTIwNg==",
    "user": {
      "login": "TomAugspurger",
      "id": 1312546,
      "node_id": "MDQ6VXNlcjEzMTI1NDY=",
      "avatar_url": "https://avatars3.githubusercontent.com/u/1312546?v=4",
      "gravatar_id": "",
      "url": "https://api.github.com/users/TomAugspurger",
      "html_url": "https://github.com/TomAugspurger",
      "followers_url": "https://api.github.com/users/TomAugspurger/followers",
      "following_url": "https://api.github.com/users/TomAugspurger/following{/other_user}",
      "gists_url": "https://api.github.com/users/TomAugspurger/gists{/gist_id}",
      "starred_url": "https://api.github.com/users/TomAugspurger/starred{/owner}{/repo}",
      "subscriptions_url": "https://api.github.com/users/TomAugspurger/subscriptions",
      "organizations_url": "https://api.github.com/users/TomAugspurger/orgs",
      "repos_url": "https://api.github.com/users/TomAugspurger/repos",
      "events_url": "https://api.github.com/users/TomAugspurger/events{/privacy}",
      "received_events_url": "https://api.github.com/users/TomAugspurger/received_events",
      "type": "User",
      "site_admin": false
    },
    "created_at": "2018-04-23T12:42:20Z",
    "updated_at": "2018-04-23T12:42:20Z",
    "author_association": "CONTRIBUTOR",
    "body": "Do you want to copy-paste my test here? https://github.com/pandas-dev/pandas/pull/20793/files#diff-fac89eff36e78c735bd1046e704780c9\r\n\r\nI prefer your check. I was duck-typing on `.values` without a `.dtype`, but just checking for `.values` more generically like you do is best."
  },
  {
    "url": "https://api.github.com/repos/pandas-dev/pandas/issues/comments/383566488",
    "html_url": "https://github.com/pandas-dev/pandas/pull/20794#issuecomment-383566488",
    "issue_url": "https://api.github.com/repos/pandas-dev/pandas/issues/20794",
    "id": 383566488,
    "node_id": "MDEyOklzc3VlQ29tbWVudDM4MzU2NjQ4OA==",
    "user": {
      "login": "jorisvandenbossche",
      "id": 1020496,
      "node_id": "MDQ6VXNlcjEwMjA0OTY=",
      "avatar_url": "https://avatars2.githubusercontent.com/u/1020496?v=4",
      "gravatar_id": "",
      "url": "https://api.github.com/users/jorisvandenbossche",
      "html_url": "https://github.com/jorisvandenbossche",
      "followers_url": "https://api.github.com/users/jorisvandenbossche/followers",
      "following_url": "https://api.github.com/users/jorisvandenbossche/following{/other_user}",
      "gists_url": "https://api.github.com/users/jorisvandenbossche/gists{/gist_id}",
      "starred_url": "https://api.github.com/users/jorisvandenbossche/starred{/owner}{/repo}",
      "subscriptions_url": "https://api.github.com/users/jorisvandenbossche/subscriptions",
      "organizations_url": "https://api.github.com/users/jorisvandenbossche/orgs",
      "repos_url": "https://api.github.com/users/jorisvandenbossche/repos",
      "events_url": "https://api.github.com/users/jorisvandenbossche/events{/privacy}",
      "received_events_url": "https://api.github.com/users/jorisvandenbossche/received_events",
      "type": "User",
      "site_admin": false
    },
    "created_at": "2018-04-23T13:00:40Z",
    "updated_at": "2018-04-23T13:00:40Z",
    "author_association": "MEMBER",
    "body": "> Do you want to copy-paste my test here? https://github.com/pandas-dev/pandas/pull/20793/files#diff-fac89eff36e78c735bd1046e704780c9\r\n\r\nwhich test do you mean?\r\n\r\n"
  },
  {
    "url": "https://api.github.com/repos/pandas-dev/pandas/issues/comments/383589327",
    "html_url": "https://github.com/pandas-dev/pandas/pull/20794#issuecomment-383589327",
    "issue_url": "https://api.github.com/repos/pandas-dev/pandas/issues/20794",
    "id": 383589327,
    "node_id": "MDEyOklzc3VlQ29tbWVudDM4MzU4OTMyNw==",
    "user": {
      "login": "codecov[bot]",
      "id": 22429695,
      "node_id": "MDM6Qm90MjI0Mjk2OTU=",
      "avatar_url": "https://avatars2.githubusercontent.com/in/254?v=4",
      "gravatar_id": "",
      "url": "https://api.github.com/users/codecov%5Bbot%5D",
      "html_url": "https://github.com/apps/codecov",
      "followers_url": "https://api.github.com/users/codecov%5Bbot%5D/followers",
      "following_url": "https://api.github.com/users/codecov%5Bbot%5D/following{/other_user}",
      "gists_url": "https://api.github.com/users/codecov%5Bbot%5D/gists{/gist_id}",
      "starred_url": "https://api.github.com/users/codecov%5Bbot%5D/starred{/owner}{/repo}",
      "subscriptions_url": "https://api.github.com/users/codecov%5Bbot%5D/subscriptions",
      "organizations_url": "https://api.github.com/users/codecov%5Bbot%5D/orgs",
      "repos_url": "https://api.github.com/users/codecov%5Bbot%5D/repos",
      "events_url": "https://api.github.com/users/codecov%5Bbot%5D/events{/privacy}",
      "received_events_url": "https://api.github.com/users/codecov%5Bbot%5D/received_events",
      "type": "Bot",
      "site_admin": false
    },
    "created_at": "2018-04-23T14:11:38Z",
    "updated_at": "2018-04-23T14:15:34Z",
    "author_association": "NONE",
    "body": "# [Codecov](https://codecov.io/gh/pandas-dev/pandas/pull/20794?src=pr&el=h1) Report\n> Merging [#20794](https://codecov.io/gh/pandas-dev/pandas/pull/20794?src=pr&el=desc) into [master](https://codecov.io/gh/pandas-dev/pandas/commit/0ae7e9090cee6e10ebb4124a0b7f3b30811ccc53?src=pr&el=desc) will **decrease** coverage by `0.02%`.\n> The diff coverage is `n/a`.\n\n[![Impacted file tree graph](https://codecov.io/gh/pandas-dev/pandas/pull/20794/graphs/tree.svg?token=eZ4WkYLtcO&src=pr&height=150&width=650)](https://codecov.io/gh/pandas-dev/pandas/pull/20794?src=pr&el=tree)\n\n```diff\n@@            Coverage Diff             @@\n##           master   #20794      +/-   ##\n==========================================\n- Coverage   91.85%   91.82%   -0.03%     \n==========================================\n  Files         153      153              \n  Lines       49308    49310       +2     \n==========================================\n- Hits        45290    45280      -10     \n- Misses       4018     4030      +12\n```\n\n| Flag | Coverage Δ | |\n|---|---|---|\n| #multiple | `90.21% <ø> (-0.03%)` | :arrow_down: |\n| #single | `41.89% <ø> (ø)` | :arrow_up: |\n\n| [Impacted Files](https://codecov.io/gh/pandas-dev/pandas/pull/20794?src=pr&el=tree) | Coverage Δ | |\n|---|---|---|\n| [pandas/core/arrays/base.py](https://codecov.io/gh/pandas-dev/pandas/pull/20794/diff?src=pr&el=tree#diff-cGFuZGFzL2NvcmUvYXJyYXlzL2Jhc2UucHk=) | `84.14% <ø> (ø)` | :arrow_up: |\n| [pandas/plotting/\\_converter.py](https://codecov.io/gh/pandas-dev/pandas/pull/20794/diff?src=pr&el=tree#diff-cGFuZGFzL3Bsb3R0aW5nL19jb252ZXJ0ZXIucHk=) | `65.07% <0%> (-1.74%)` | :arrow_down: |\n| [pandas/core/indexes/base.py](https://codecov.io/gh/pandas-dev/pandas/pull/20794/diff?src=pr&el=tree#diff-cGFuZGFzL2NvcmUvaW5kZXhlcy9iYXNlLnB5) | `96.68% <0%> (ø)` | :arrow_up: |\n| [pandas/core/frame.py](https://codecov.io/gh/pandas-dev/pandas/pull/20794/diff?src=pr&el=tree#diff-cGFuZGFzL2NvcmUvZnJhbWUucHk=) | `97.17% <0%> (ø)` | :arrow_up: |\n| [pandas/core/accessor.py](https://codecov.io/gh/pandas-dev/pandas/pull/20794/diff?src=pr&el=tree#diff-cGFuZGFzL2NvcmUvYWNjZXNzb3IucHk=) | `98.71% <0%> (+0.01%)` | :arrow_up: |\n\n------\n\n[Continue to review full report at Codecov](https://codecov.io/gh/pandas-dev/pandas/pull/20794?src=pr&el=continue).\n> **Legend** - [Click here to learn more](https://docs.codecov.io/docs/codecov-delta)\n> `Δ = absolute <relative> (impact)`, `ø = not affected`, `? = missing data`\n> Powered by [Codecov](https://codecov.io/gh/pandas-dev/pandas/pull/20794?src=pr&el=footer). Last update [0ae7e90...a57f8e0](https://codecov.io/gh/pandas-dev/pandas/pull/20794?src=pr&el=lastupdated). Read the [comment docs](https://docs.codecov.io/docs/pull-request-comments).\n"
  },
  {
    "url": "https://api.github.com/repos/pandas-dev/pandas/issues/comments/383883241",
    "html_url": "https://github.com/pandas-dev/pandas/pull/20794#issuecomment-383883241",
    "issue_url": "https://api.github.com/repos/pandas-dev/pandas/issues/20794",
    "id": 383883241,
    "node_id": "MDEyOklzc3VlQ29tbWVudDM4Mzg4MzI0MQ==",
    "user": {
      "login": "jreback",
      "id": 953992,
      "node_id": "MDQ6VXNlcjk1Mzk5Mg==",
      "avatar_url": "https://avatars2.githubusercontent.com/u/953992?v=4",
      "gravatar_id": "",
      "url": "https://api.github.com/users/jreback",
      "html_url": "https://github.com/jreback",
      "followers_url": "https://api.github.com/users/jreback/followers",
      "following_url": "https://api.github.com/users/jreback/following{/other_user}",
      "gists_url": "https://api.github.com/users/jreback/gists{/gist_id}",
      "starred_url": "https://api.github.com/users/jreback/starred{/owner}{/repo}",
      "subscriptions_url": "https://api.github.com/users/jreback/subscriptions",
      "organizations_url": "https://api.github.com/users/jreback/orgs",
      "repos_url": "https://api.github.com/users/jreback/repos",
      "events_url": "https://api.github.com/users/jreback/events{/privacy}",
      "received_events_url": "https://api.github.com/users/jreback/received_events",
      "type": "User",
      "site_admin": false
    },
    "created_at": "2018-04-24T10:28:35Z",
    "updated_at": "2018-04-24T10:28:35Z",
    "author_association": "CONTRIBUTOR",
    "body": "thanks!"
  }
]
