[
  {
    "url": "https://api.github.com/repos/pandas-dev/pandas/issues/comments/29418666",
    "html_url": "https://github.com/pandas-dev/pandas/issues/5536#issuecomment-29418666",
    "issue_url": "https://api.github.com/repos/pandas-dev/pandas/issues/5536",
    "id": 29418666,
    "node_id": "MDEyOklzc3VlQ29tbWVudDI5NDE4NjY2",
    "user": {
      "login": "jreback",
      "id": 953992,
      "node_id": "MDQ6VXNlcjk1Mzk5Mg==",
      "avatar_url": "https://avatars2.githubusercontent.com/u/953992?v=4",
      "gravatar_id": "",
      "url": "https://api.github.com/users/jreback",
      "html_url": "https://github.com/jreback",
      "followers_url": "https://api.github.com/users/jreback/followers",
      "following_url": "https://api.github.com/users/jreback/following{/other_user}",
      "gists_url": "https://api.github.com/users/jreback/gists{/gist_id}",
      "starred_url": "https://api.github.com/users/jreback/starred{/owner}{/repo}",
      "subscriptions_url": "https://api.github.com/users/jreback/subscriptions",
      "organizations_url": "https://api.github.com/users/jreback/orgs",
      "repos_url": "https://api.github.com/users/jreback/repos",
      "events_url": "https://api.github.com/users/jreback/events{/privacy}",
      "received_events_url": "https://api.github.com/users/jreback/received_events",
      "type": "User",
      "site_admin": false
    },
    "created_at": "2013-11-27T20:44:24Z",
    "updated_at": "2013-11-27T20:44:24Z",
    "author_association": "CONTRIBUTOR",
    "body": "can you retry this with current master? this was a problem in win32 as well (which is now fixed)\n"
  },
  {
    "url": "https://api.github.com/repos/pandas-dev/pandas/issues/comments/29561557",
    "html_url": "https://github.com/pandas-dev/pandas/issues/5536#issuecomment-29561557",
    "issue_url": "https://api.github.com/repos/pandas-dev/pandas/issues/5536",
    "id": 29561557,
    "node_id": "MDEyOklzc3VlQ29tbWVudDI5NTYxNTU3",
    "user": {
      "login": "neirbowj",
      "id": 1879063,
      "node_id": "MDQ6VXNlcjE4NzkwNjM=",
      "avatar_url": "https://avatars0.githubusercontent.com/u/1879063?v=4",
      "gravatar_id": "",
      "url": "https://api.github.com/users/neirbowj",
      "html_url": "https://github.com/neirbowj",
      "followers_url": "https://api.github.com/users/neirbowj/followers",
      "following_url": "https://api.github.com/users/neirbowj/following{/other_user}",
      "gists_url": "https://api.github.com/users/neirbowj/gists{/gist_id}",
      "starred_url": "https://api.github.com/users/neirbowj/starred{/owner}{/repo}",
      "subscriptions_url": "https://api.github.com/users/neirbowj/subscriptions",
      "organizations_url": "https://api.github.com/users/neirbowj/orgs",
      "repos_url": "https://api.github.com/users/neirbowj/repos",
      "events_url": "https://api.github.com/users/neirbowj/events{/privacy}",
      "received_events_url": "https://api.github.com/users/neirbowj/received_events",
      "type": "User",
      "site_admin": false
    },
    "created_at": "2013-11-30T21:34:06Z",
    "updated_at": "2013-11-30T21:34:06Z",
    "author_association": "CONTRIBUTOR",
    "body": "Looks good with 0.13.0rc1 under Python 2.7.6.\n\n```\n$ nosetests -v pandas.tools.tests.test_tile:TestCut.test_inf_handling\ntest_inf_handling (pandas.tools.tests.test_tile.TestCut) ... ok\n\n----------------------------------------------------------------------\nRan 1 test in 0.003s\n\nOK\n```\n\nThank you.\n"
  },
  {
    "url": "https://api.github.com/repos/pandas-dev/pandas/issues/comments/29561591",
    "html_url": "https://github.com/pandas-dev/pandas/issues/5536#issuecomment-29561591",
    "issue_url": "https://api.github.com/repos/pandas-dev/pandas/issues/5536",
    "id": 29561591,
    "node_id": "MDEyOklzc3VlQ29tbWVudDI5NTYxNTkx",
    "user": {
      "login": "jreback",
      "id": 953992,
      "node_id": "MDQ6VXNlcjk1Mzk5Mg==",
      "avatar_url": "https://avatars2.githubusercontent.com/u/953992?v=4",
      "gravatar_id": "",
      "url": "https://api.github.com/users/jreback",
      "html_url": "https://github.com/jreback",
      "followers_url": "https://api.github.com/users/jreback/followers",
      "following_url": "https://api.github.com/users/jreback/following{/other_user}",
      "gists_url": "https://api.github.com/users/jreback/gists{/gist_id}",
      "starred_url": "https://api.github.com/users/jreback/starred{/owner}{/repo}",
      "subscriptions_url": "https://api.github.com/users/jreback/subscriptions",
      "organizations_url": "https://api.github.com/users/jreback/orgs",
      "repos_url": "https://api.github.com/users/jreback/repos",
      "events_url": "https://api.github.com/users/jreback/events{/privacy}",
      "received_events_url": "https://api.github.com/users/jreback/received_events",
      "type": "User",
      "site_admin": false
    },
    "created_at": "2013-11-30T21:36:00Z",
    "updated_at": "2013-11-30T21:36:00Z",
    "author_association": "CONTRIBUTOR",
    "body": "gr8\npls post any further testing issues you have \n"
  }
]
