[
  {
    "url": "https://api.github.com/repos/pandas-dev/pandas/issues/comments/36465809",
    "html_url": "https://github.com/pandas-dev/pandas/issues/6512#issuecomment-36465809",
    "issue_url": "https://api.github.com/repos/pandas-dev/pandas/issues/6512",
    "id": 36465809,
    "node_id": "MDEyOklzc3VlQ29tbWVudDM2NDY1ODA5",
    "user": {
      "login": "danielballan",
      "id": 2279598,
      "node_id": "MDQ6VXNlcjIyNzk1OTg=",
      "avatar_url": "https://avatars3.githubusercontent.com/u/2279598?v=4",
      "gravatar_id": "",
      "url": "https://api.github.com/users/danielballan",
      "html_url": "https://github.com/danielballan",
      "followers_url": "https://api.github.com/users/danielballan/followers",
      "following_url": "https://api.github.com/users/danielballan/following{/other_user}",
      "gists_url": "https://api.github.com/users/danielballan/gists{/gist_id}",
      "starred_url": "https://api.github.com/users/danielballan/starred{/owner}{/repo}",
      "subscriptions_url": "https://api.github.com/users/danielballan/subscriptions",
      "organizations_url": "https://api.github.com/users/danielballan/orgs",
      "repos_url": "https://api.github.com/users/danielballan/repos",
      "events_url": "https://api.github.com/users/danielballan/events{/privacy}",
      "received_events_url": "https://api.github.com/users/danielballan/received_events",
      "type": "User",
      "site_admin": false
    },
    "created_at": "2014-03-02T20:37:03Z",
    "updated_at": "2014-03-02T20:37:03Z",
    "author_association": "CONTRIBUTOR",
    "body": "Woah, this _is_ bad. Very surprised the huge number of tests does not cover this. I'm too busy to dig into this this week, but I can get into it next week. Let me know if you make any progress in the meantime.\n"
  },
  {
    "url": "https://api.github.com/repos/pandas-dev/pandas/issues/comments/36483505",
    "html_url": "https://github.com/pandas-dev/pandas/issues/6512#issuecomment-36483505",
    "issue_url": "https://api.github.com/repos/pandas-dev/pandas/issues/6512",
    "id": 36483505,
    "node_id": "MDEyOklzc3VlQ29tbWVudDM2NDgzNTA1",
    "user": {
      "login": "naught101",
      "id": 167164,
      "node_id": "MDQ6VXNlcjE2NzE2NA==",
      "avatar_url": "https://avatars3.githubusercontent.com/u/167164?v=4",
      "gravatar_id": "",
      "url": "https://api.github.com/users/naught101",
      "html_url": "https://github.com/naught101",
      "followers_url": "https://api.github.com/users/naught101/followers",
      "following_url": "https://api.github.com/users/naught101/following{/other_user}",
      "gists_url": "https://api.github.com/users/naught101/gists{/gist_id}",
      "starred_url": "https://api.github.com/users/naught101/starred{/owner}{/repo}",
      "subscriptions_url": "https://api.github.com/users/naught101/subscriptions",
      "organizations_url": "https://api.github.com/users/naught101/orgs",
      "repos_url": "https://api.github.com/users/naught101/repos",
      "events_url": "https://api.github.com/users/naught101/events{/privacy}",
      "received_events_url": "https://api.github.com/users/naught101/received_events",
      "type": "User",
      "site_admin": false
    },
    "created_at": "2014-03-03T05:55:21Z",
    "updated_at": "2014-03-03T05:55:21Z",
    "author_association": "NONE",
    "body": "Not entirely sure, but this might be related: http://stackoverflow.com/questions/22139053/grouped-function-between-2-columns-in-a-pandas-dataframe\n\n```\ndf = pandas.DataFrame({\"Dummy\":[1,2]*6, \"X\":[1,3,7]*4, \n                       \"Y\":[2,3,4]*4, \"group\":[\"A\",\"B\"]*6})\ndf.groupby('group')[:,['X', 'Y']].head(1)\n\n         Dummy  X  Y group\ngroup                     \nA     0      1  1  2     A\nB     1      2  3  3     B\n\n[2 rows x 4 columns]\n```\n"
  },
  {
    "url": "https://api.github.com/repos/pandas-dev/pandas/issues/comments/36485001",
    "html_url": "https://github.com/pandas-dev/pandas/issues/6512#issuecomment-36485001",
    "issue_url": "https://api.github.com/repos/pandas-dev/pandas/issues/6512",
    "id": 36485001,
    "node_id": "MDEyOklzc3VlQ29tbWVudDM2NDg1MDAx",
    "user": {
      "login": "hayd",
      "id": 1931852,
      "node_id": "MDQ6VXNlcjE5MzE4NTI=",
      "avatar_url": "https://avatars2.githubusercontent.com/u/1931852?v=4",
      "gravatar_id": "",
      "url": "https://api.github.com/users/hayd",
      "html_url": "https://github.com/hayd",
      "followers_url": "https://api.github.com/users/hayd/followers",
      "following_url": "https://api.github.com/users/hayd/following{/other_user}",
      "gists_url": "https://api.github.com/users/hayd/gists{/gist_id}",
      "starred_url": "https://api.github.com/users/hayd/starred{/owner}{/repo}",
      "subscriptions_url": "https://api.github.com/users/hayd/subscriptions",
      "organizations_url": "https://api.github.com/users/hayd/orgs",
      "repos_url": "https://api.github.com/users/hayd/repos",
      "events_url": "https://api.github.com/users/hayd/events{/privacy}",
      "received_events_url": "https://api.github.com/users/hayd/received_events",
      "type": "User",
      "site_admin": false
    },
    "created_at": "2014-03-03T06:40:10Z",
    "updated_at": "2014-03-03T06:40:10Z",
    "author_association": "CONTRIBUTOR",
    "body": "@naught101 I posted your find as #6524.\n\nI suspect that it's because this syntax is not supported:\n\n```\ng[:,['X', 'Y']]\ng[['X', 'Y']]\n```\n"
  },
  {
    "url": "https://api.github.com/repos/pandas-dev/pandas/issues/comments/37067062",
    "html_url": "https://github.com/pandas-dev/pandas/issues/6512#issuecomment-37067062",
    "issue_url": "https://api.github.com/repos/pandas-dev/pandas/issues/6512",
    "id": 37067062,
    "node_id": "MDEyOklzc3VlQ29tbWVudDM3MDY3MDYy",
    "user": {
      "login": "hayd",
      "id": 1931852,
      "node_id": "MDQ6VXNlcjE5MzE4NTI=",
      "avatar_url": "https://avatars2.githubusercontent.com/u/1931852?v=4",
      "gravatar_id": "",
      "url": "https://api.github.com/users/hayd",
      "html_url": "https://github.com/hayd",
      "followers_url": "https://api.github.com/users/hayd/followers",
      "following_url": "https://api.github.com/users/hayd/following{/other_user}",
      "gists_url": "https://api.github.com/users/hayd/gists{/gist_id}",
      "starred_url": "https://api.github.com/users/hayd/starred{/owner}{/repo}",
      "subscriptions_url": "https://api.github.com/users/hayd/subscriptions",
      "organizations_url": "https://api.github.com/users/hayd/orgs",
      "repos_url": "https://api.github.com/users/hayd/repos",
      "events_url": "https://api.github.com/users/hayd/events{/privacy}",
      "received_events_url": "https://api.github.com/users/hayd/received_events",
      "type": "User",
      "site_admin": false
    },
    "created_at": "2014-03-07T21:00:08Z",
    "updated_at": "2014-03-07T21:00:08Z",
    "author_association": "CONTRIBUTOR",
    "body": "Trivial fix after #6570, use `selected_obj` rather than `objwithexclusions` on first line.\n"
  },
  {
    "url": "https://api.github.com/repos/pandas-dev/pandas/issues/comments/37252802",
    "html_url": "https://github.com/pandas-dev/pandas/issues/6512#issuecomment-37252802",
    "issue_url": "https://api.github.com/repos/pandas-dev/pandas/issues/6512",
    "id": 37252802,
    "node_id": "MDEyOklzc3VlQ29tbWVudDM3MjUyODAy",
    "user": {
      "login": "hayd",
      "id": 1931852,
      "node_id": "MDQ6VXNlcjE5MzE4NTI=",
      "avatar_url": "https://avatars2.githubusercontent.com/u/1931852?v=4",
      "gravatar_id": "",
      "url": "https://api.github.com/users/hayd",
      "html_url": "https://github.com/hayd",
      "followers_url": "https://api.github.com/users/hayd/followers",
      "following_url": "https://api.github.com/users/hayd/following{/other_user}",
      "gists_url": "https://api.github.com/users/hayd/gists{/gist_id}",
      "starred_url": "https://api.github.com/users/hayd/starred{/owner}{/repo}",
      "subscriptions_url": "https://api.github.com/users/hayd/subscriptions",
      "organizations_url": "https://api.github.com/users/hayd/orgs",
      "repos_url": "https://api.github.com/users/hayd/repos",
      "events_url": "https://api.github.com/users/hayd/events{/privacy}",
      "received_events_url": "https://api.github.com/users/hayd/received_events",
      "type": "User",
      "site_admin": false
    },
    "created_at": "2014-03-11T00:54:30Z",
    "updated_at": "2014-03-11T00:54:30Z",
    "author_association": "CONTRIBUTOR",
    "body": "fixed!\n"
  }
]
