[
  {
    "url": "https://api.github.com/repos/ipython/ipython/issues/comments/1881248",
    "html_url": "https://github.com/ipython/ipython/issues/390#issuecomment-1881248",
    "issue_url": "https://api.github.com/repos/ipython/ipython/issues/390",
    "id": 1881248,
    "node_id": "MDEyOklzc3VlQ29tbWVudDE4ODEyNDg=",
    "user": {
      "login": "mhoffman",
      "id": 139379,
      "node_id": "MDQ6VXNlcjEzOTM3OQ==",
      "avatar_url": "https://avatars3.githubusercontent.com/u/139379?v=4",
      "gravatar_id": "",
      "url": "https://api.github.com/users/mhoffman",
      "html_url": "https://github.com/mhoffman",
      "followers_url": "https://api.github.com/users/mhoffman/followers",
      "following_url": "https://api.github.com/users/mhoffman/following{/other_user}",
      "gists_url": "https://api.github.com/users/mhoffman/gists{/gist_id}",
      "starred_url": "https://api.github.com/users/mhoffman/starred{/owner}{/repo}",
      "subscriptions_url": "https://api.github.com/users/mhoffman/subscriptions",
      "organizations_url": "https://api.github.com/users/mhoffman/orgs",
      "repos_url": "https://api.github.com/users/mhoffman/repos",
      "events_url": "https://api.github.com/users/mhoffman/events{/privacy}",
      "received_events_url": "https://api.github.com/users/mhoffman/received_events",
      "type": "User",
      "site_admin": false
    },
    "created_at": "2011-08-23T16:05:57Z",
    "updated_at": "2011-08-23T16:05:57Z",
    "author_association": "NONE",
    "body": "Yes, please, add CDPATH support. I use a lot and like it and it keeps me from making the switch.\n"
  },
  {
    "url": "https://api.github.com/repos/ipython/ipython/issues/comments/18892499",
    "html_url": "https://github.com/ipython/ipython/issues/390#issuecomment-18892499",
    "issue_url": "https://api.github.com/repos/ipython/ipython/issues/390",
    "id": 18892499,
    "node_id": "MDEyOklzc3VlQ29tbWVudDE4ODkyNDk5",
    "user": {
      "login": "jagguli",
      "id": 74574,
      "node_id": "MDQ6VXNlcjc0NTc0",
      "avatar_url": "https://avatars2.githubusercontent.com/u/74574?v=4",
      "gravatar_id": "",
      "url": "https://api.github.com/users/jagguli",
      "html_url": "https://github.com/jagguli",
      "followers_url": "https://api.github.com/users/jagguli/followers",
      "following_url": "https://api.github.com/users/jagguli/following{/other_user}",
      "gists_url": "https://api.github.com/users/jagguli/gists{/gist_id}",
      "starred_url": "https://api.github.com/users/jagguli/starred{/owner}{/repo}",
      "subscriptions_url": "https://api.github.com/users/jagguli/subscriptions",
      "organizations_url": "https://api.github.com/users/jagguli/orgs",
      "repos_url": "https://api.github.com/users/jagguli/repos",
      "events_url": "https://api.github.com/users/jagguli/events{/privacy}",
      "received_events_url": "https://api.github.com/users/jagguli/received_events",
      "type": "User",
      "site_admin": false
    },
    "created_at": "2013-06-04T07:05:30Z",
    "updated_at": "2013-06-04T07:05:30Z",
    "author_association": "NONE",
    "body": "+1\n"
  },
  {
    "url": "https://api.github.com/repos/ipython/ipython/issues/comments/18892643",
    "html_url": "https://github.com/ipython/ipython/issues/390#issuecomment-18892643",
    "issue_url": "https://api.github.com/repos/ipython/ipython/issues/390",
    "id": 18892643,
    "node_id": "MDEyOklzc3VlQ29tbWVudDE4ODkyNjQz",
    "user": {
      "login": "jagguli",
      "id": 74574,
      "node_id": "MDQ6VXNlcjc0NTc0",
      "avatar_url": "https://avatars2.githubusercontent.com/u/74574?v=4",
      "gravatar_id": "",
      "url": "https://api.github.com/users/jagguli",
      "html_url": "https://github.com/jagguli",
      "followers_url": "https://api.github.com/users/jagguli/followers",
      "following_url": "https://api.github.com/users/jagguli/following{/other_user}",
      "gists_url": "https://api.github.com/users/jagguli/gists{/gist_id}",
      "starred_url": "https://api.github.com/users/jagguli/starred{/owner}{/repo}",
      "subscriptions_url": "https://api.github.com/users/jagguli/subscriptions",
      "organizations_url": "https://api.github.com/users/jagguli/orgs",
      "repos_url": "https://api.github.com/users/jagguli/repos",
      "events_url": "https://api.github.com/users/jagguli/events{/privacy}",
      "received_events_url": "https://api.github.com/users/jagguli/received_events",
      "type": "User",
      "site_admin": false
    },
    "created_at": "2013-06-04T07:10:20Z",
    "updated_at": "2013-06-04T07:14:24Z",
    "author_association": "NONE",
    "body": "although some of this functionality is provided by %bookmark, maybe just provide a mechanism to automatically add bookmarks from a variable ?\n\nOn second thought its quiet different, for example you cant get readline support off of bookmarks \n"
  }
]
