[
  {
    "url": "https://api.github.com/repos/ipython/ipython/issues/comments/239617817",
    "html_url": "https://github.com/ipython/ipython/issues/9869#issuecomment-239617817",
    "issue_url": "https://api.github.com/repos/ipython/ipython/issues/9869",
    "id": 239617817,
    "node_id": "MDEyOklzc3VlQ29tbWVudDIzOTYxNzgxNw==",
    "user": {
      "login": "takluyver",
      "id": 327925,
      "node_id": "MDQ6VXNlcjMyNzkyNQ==",
      "avatar_url": "https://avatars3.githubusercontent.com/u/327925?v=4",
      "gravatar_id": "",
      "url": "https://api.github.com/users/takluyver",
      "html_url": "https://github.com/takluyver",
      "followers_url": "https://api.github.com/users/takluyver/followers",
      "following_url": "https://api.github.com/users/takluyver/following{/other_user}",
      "gists_url": "https://api.github.com/users/takluyver/gists{/gist_id}",
      "starred_url": "https://api.github.com/users/takluyver/starred{/owner}{/repo}",
      "subscriptions_url": "https://api.github.com/users/takluyver/subscriptions",
      "organizations_url": "https://api.github.com/users/takluyver/orgs",
      "repos_url": "https://api.github.com/users/takluyver/repos",
      "events_url": "https://api.github.com/users/takluyver/events{/privacy}",
      "received_events_url": "https://api.github.com/users/takluyver/received_events",
      "type": "User",
      "site_admin": false
    },
    "created_at": "2016-08-13T12:11:20Z",
    "updated_at": "2016-08-13T12:11:20Z",
    "author_association": "MEMBER",
    "body": "How are you installing that? IPython should create `ipython3` only if it's installed by Python 3.\n"
  },
  {
    "url": "https://api.github.com/repos/ipython/ipython/issues/comments/239617883",
    "html_url": "https://github.com/ipython/ipython/issues/9869#issuecomment-239617883",
    "issue_url": "https://api.github.com/repos/ipython/ipython/issues/9869",
    "id": 239617883,
    "node_id": "MDEyOklzc3VlQ29tbWVudDIzOTYxNzg4Mw==",
    "user": {
      "login": "takluyver",
      "id": 327925,
      "node_id": "MDQ6VXNlcjMyNzkyNQ==",
      "avatar_url": "https://avatars3.githubusercontent.com/u/327925?v=4",
      "gravatar_id": "",
      "url": "https://api.github.com/users/takluyver",
      "html_url": "https://github.com/takluyver",
      "followers_url": "https://api.github.com/users/takluyver/followers",
      "following_url": "https://api.github.com/users/takluyver/following{/other_user}",
      "gists_url": "https://api.github.com/users/takluyver/gists{/gist_id}",
      "starred_url": "https://api.github.com/users/takluyver/starred{/owner}{/repo}",
      "subscriptions_url": "https://api.github.com/users/takluyver/subscriptions",
      "organizations_url": "https://api.github.com/users/takluyver/orgs",
      "repos_url": "https://api.github.com/users/takluyver/repos",
      "events_url": "https://api.github.com/users/takluyver/events{/privacy}",
      "received_events_url": "https://api.github.com/users/takluyver/received_events",
      "type": "User",
      "site_admin": false
    },
    "created_at": "2016-08-13T12:13:31Z",
    "updated_at": "2016-08-13T12:13:31Z",
    "author_association": "MEMBER",
    "body": "Rats, we've made a universal wheel (`py2.py3`). @Carreau, we need to do separate Python 2 and 3 wheels so that the scripts get installed correctly.\n"
  },
  {
    "url": "https://api.github.com/repos/ipython/ipython/issues/comments/239622462",
    "html_url": "https://github.com/ipython/ipython/issues/9869#issuecomment-239622462",
    "issue_url": "https://api.github.com/repos/ipython/ipython/issues/9869",
    "id": 239622462,
    "node_id": "MDEyOklzc3VlQ29tbWVudDIzOTYyMjQ2Mg==",
    "user": {
      "login": "takluyver",
      "id": 327925,
      "node_id": "MDQ6VXNlcjMyNzkyNQ==",
      "avatar_url": "https://avatars3.githubusercontent.com/u/327925?v=4",
      "gravatar_id": "",
      "url": "https://api.github.com/users/takluyver",
      "html_url": "https://github.com/takluyver",
      "followers_url": "https://api.github.com/users/takluyver/followers",
      "following_url": "https://api.github.com/users/takluyver/following{/other_user}",
      "gists_url": "https://api.github.com/users/takluyver/gists{/gist_id}",
      "starred_url": "https://api.github.com/users/takluyver/starred{/owner}{/repo}",
      "subscriptions_url": "https://api.github.com/users/takluyver/subscriptions",
      "organizations_url": "https://api.github.com/users/takluyver/orgs",
      "repos_url": "https://api.github.com/users/takluyver/repos",
      "events_url": "https://api.github.com/users/takluyver/events{/privacy}",
      "received_events_url": "https://api.github.com/users/takluyver/received_events",
      "type": "User",
      "site_admin": false
    },
    "created_at": "2016-08-13T14:04:16Z",
    "updated_at": "2016-08-13T14:04:16Z",
    "author_association": "MEMBER",
    "body": "I've released 5.1, so this should work as expected again - installing on Python 3 will create `ipython` and `ipython3`, installing on Python 2, `ipython` and `ipython2`.\n"
  },
  {
    "url": "https://api.github.com/repos/ipython/ipython/issues/comments/239648292",
    "html_url": "https://github.com/ipython/ipython/issues/9869#issuecomment-239648292",
    "issue_url": "https://api.github.com/repos/ipython/ipython/issues/9869",
    "id": 239648292,
    "node_id": "MDEyOklzc3VlQ29tbWVudDIzOTY0ODI5Mg==",
    "user": {
      "login": "Carreau",
      "id": 335567,
      "node_id": "MDQ6VXNlcjMzNTU2Nw==",
      "avatar_url": "https://avatars3.githubusercontent.com/u/335567?v=4",
      "gravatar_id": "",
      "url": "https://api.github.com/users/Carreau",
      "html_url": "https://github.com/Carreau",
      "followers_url": "https://api.github.com/users/Carreau/followers",
      "following_url": "https://api.github.com/users/Carreau/following{/other_user}",
      "gists_url": "https://api.github.com/users/Carreau/gists{/gist_id}",
      "starred_url": "https://api.github.com/users/Carreau/starred{/owner}{/repo}",
      "subscriptions_url": "https://api.github.com/users/Carreau/subscriptions",
      "organizations_url": "https://api.github.com/users/Carreau/orgs",
      "repos_url": "https://api.github.com/users/Carreau/repos",
      "events_url": "https://api.github.com/users/Carreau/events{/privacy}",
      "received_events_url": "https://api.github.com/users/Carreau/received_events",
      "type": "User",
      "site_admin": false
    },
    "created_at": "2016-08-14T00:02:14Z",
    "updated_at": "2016-08-14T00:02:14Z",
    "author_association": "MEMBER",
    "body": "> Rats, we've made a universal wheel (py2.py3). @Carreau, we need to do separate Python 2 and 3 wheels so that the scripts get installed correctly.\n\nWe need to have a test, or documentation in the release process for this. Otherwise we will make the mistake again.\n"
  },
  {
    "url": "https://api.github.com/repos/ipython/ipython/issues/comments/239648308",
    "html_url": "https://github.com/ipython/ipython/issues/9869#issuecomment-239648308",
    "issue_url": "https://api.github.com/repos/ipython/ipython/issues/9869",
    "id": 239648308,
    "node_id": "MDEyOklzc3VlQ29tbWVudDIzOTY0ODMwOA==",
    "user": {
      "login": "Carreau",
      "id": 335567,
      "node_id": "MDQ6VXNlcjMzNTU2Nw==",
      "avatar_url": "https://avatars3.githubusercontent.com/u/335567?v=4",
      "gravatar_id": "",
      "url": "https://api.github.com/users/Carreau",
      "html_url": "https://github.com/Carreau",
      "followers_url": "https://api.github.com/users/Carreau/followers",
      "following_url": "https://api.github.com/users/Carreau/following{/other_user}",
      "gists_url": "https://api.github.com/users/Carreau/gists{/gist_id}",
      "starred_url": "https://api.github.com/users/Carreau/starred{/owner}{/repo}",
      "subscriptions_url": "https://api.github.com/users/Carreau/subscriptions",
      "organizations_url": "https://api.github.com/users/Carreau/orgs",
      "repos_url": "https://api.github.com/users/Carreau/repos",
      "events_url": "https://api.github.com/users/Carreau/events{/privacy}",
      "received_events_url": "https://api.github.com/users/Carreau/received_events",
      "type": "User",
      "site_admin": false
    },
    "created_at": "2016-08-14T00:02:40Z",
    "updated_at": "2016-08-14T00:02:40Z",
    "author_association": "MEMBER",
    "body": "> I've released 5.1\n\nWoooo !\n"
  },
  {
    "url": "https://api.github.com/repos/ipython/ipython/issues/comments/239656663",
    "html_url": "https://github.com/ipython/ipython/issues/9869#issuecomment-239656663",
    "issue_url": "https://api.github.com/repos/ipython/ipython/issues/9869",
    "id": 239656663,
    "node_id": "MDEyOklzc3VlQ29tbWVudDIzOTY1NjY2Mw==",
    "user": {
      "login": "willingc",
      "id": 2680980,
      "node_id": "MDQ6VXNlcjI2ODA5ODA=",
      "avatar_url": "https://avatars3.githubusercontent.com/u/2680980?v=4",
      "gravatar_id": "",
      "url": "https://api.github.com/users/willingc",
      "html_url": "https://github.com/willingc",
      "followers_url": "https://api.github.com/users/willingc/followers",
      "following_url": "https://api.github.com/users/willingc/following{/other_user}",
      "gists_url": "https://api.github.com/users/willingc/gists{/gist_id}",
      "starred_url": "https://api.github.com/users/willingc/starred{/owner}{/repo}",
      "subscriptions_url": "https://api.github.com/users/willingc/subscriptions",
      "organizations_url": "https://api.github.com/users/willingc/orgs",
      "repos_url": "https://api.github.com/users/willingc/repos",
      "events_url": "https://api.github.com/users/willingc/events{/privacy}",
      "received_events_url": "https://api.github.com/users/willingc/received_events",
      "type": "User",
      "site_admin": false
    },
    "created_at": "2016-08-14T05:16:35Z",
    "updated_at": "2016-08-14T05:16:35Z",
    "author_association": "MEMBER",
    "body": "Great job @takluyver 🎆 \n"
  }
]
